Matplotshorts/Matplotshorts.py
Matplotshorts/__init__.py
Matplotshorts-0.0.8.dist-info/LICENSE.txt
Matplotshorts-0.0.8.dist-info/METADATA
Matplotshorts-0.0.8.dist-info/WHEEL
Matplotshorts-0.0.8.dist-info/top_level.txt
Matplotshorts-0.0.8.dist-info/RECORD
