Metadata-Version: 2.1
Name: Matplotshorts
Version: 0.0.8
Summary: Usefull wrapper methods for matplot
Home-page: UNKNOWN
Author: Dennis Maier
Author-email: dennis@dennis-maier.de
License: MIT
Platform: UNKNOWN
Classifier: Programming Language :: Python :: 3
Classifier: License :: OSI Approved :: MIT License
Classifier: Operating System :: OS Independent
Requires-Dist: matplotlib
